dump_env/__init__.py
dump_env/cli.py
dump_env/dumper.py
dump_env/exceptions.py
dump_env-1.6.0.dist-info/LICENSE
dump_env-1.6.0.dist-info/METADATA
dump_env-1.6.0.dist-info/WHEEL
dump_env-1.6.0.dist-info/entry_points.txt
dump_env-1.6.0.dist-info/RECORD
