Metadata-Version: 2.3
Name: dump-env
Version: 1.6.0
Summary: A utility tool to create .env files
License: MIT
Keywords: dotenv,.env,templates,secrets,CI/CD
Author: Nikita Sobolev
Author-email: mail@sobolevn.me
Requires-Python: >=3.10,<4.0
Classifier: Development Status :: 5 - Production/Stable
Classifier: Environment :: Console
Classifier: Intended Audience :: Developers
Classifier: License :: OSI Approved :: MIT License
Classifier: Operating System :: OS Independent
Classifier: Programming Language :: Python :: 3
Classifier: Programming Language :: Python :: 3.10
Classifier: Programming Language :: Python :: 3.11
Classifier: Programming Language :: Python :: 3.12
Classifier: Programming Language :: Python :: 3.13
Classifier: Typing :: Typed
Project-URL: Homepage, https://dump-env.readthedocs.io
Project-URL: Repository, https://github.com/wemake-services/dump-env
